firedantic_mixin/__init__.py
firedantic_mixin/mixin.py
firedantic_mixin-1.0.8.dist-info/LICENSE.md
firedantic_mixin-1.0.8.dist-info/METADATA
firedantic_mixin-1.0.8.dist-info/WHEEL
firedantic_mixin-1.0.8.dist-info/RECORD
