Metadata-Version: 2.1
Name: firedantic-mixin
Version: 1.0.8
Summary: Quick mixin to provide basic features to firedantic
License: CC-BY-4.0
Author: patrick o'leary
Author-email: pjaol@pjaol.com
Requires-Python: >=3.11,<4.0
Classifier: License :: Other/Proprietary License
Classifier: Programming Language :: Python :: 3
Classifier: Programming Language :: Python :: 3.11
Requires-Dist: firedantic (>=0.4.0,<0.5.0)
